phlower/__init__.py
phlower/_base/__init__.py
phlower/_base/_batch.py
phlower/_base/_dimension.py
phlower/_base/_functionals/__init__.py
phlower/_base/_functionals/_broadcast_to.py
phlower/_base/_functionals/_check.py
phlower/_base/_functionals/_concatenate.py
phlower/_base/_functionals/_to_batch.py
phlower/_base/_functionals/_unbatch.py
phlower/_base/array/__init__.py
phlower/_base/array/_interface_wrapper.py
phlower/_base/array/_phlower_array.py
phlower/_base/array/dense/__init__.py
phlower/_base/array/dense/_ndarray_wrapper.py
phlower/_base/array/sparse/__init__.py
phlower/_base/array/sparse/_sparse_array_wrapper.py
phlower/_base/tensors/__init__.py
phlower/_base/tensors/_dimension_tensor.py
phlower/_base/tensors/_interface.py
phlower/_base/tensors/_phlower_tensor.py
phlower/_base/tensors/_tensor_shape.py
phlower/_fields/__init__.py
phlower/_fields/_simulation_field.py
phlower/collections/__init__.py
phlower/collections/arrays/__init__.py
phlower/collections/arrays/_arrays_dict.py
phlower/collections/tensors/__init__.py
phlower/collections/tensors/_tensor_collections.py
phlower/data/__init__.py
phlower/data/_collate_fn.py
phlower/data/_data_loader.py
phlower/data/_datasets.py
phlower/data/_lumped_data.py
phlower/io/__init__.py
phlower/io/_directory.py
phlower/io/_file_builder.py
phlower/io/_files/__init__.py
phlower/io/_files/_interface.py
phlower/io/_files/checkpoint_file.py
phlower/io/_files/numpy_file.py
phlower/io/_files/yaml_file.py
phlower/io/_model_selector.py
phlower/nn/__init__.py
phlower/nn/_core_modules/__init__.py
phlower/nn/_core_modules/_accessor.py
phlower/nn/_core_modules/_concatenator.py
phlower/nn/_core_modules/_contraction.py
phlower/nn/_core_modules/_deepsets.py
phlower/nn/_core_modules/_dirichlet.py
phlower/nn/_core_modules/_einsum.py
phlower/nn/_core_modules/_en_equivariant_mlp.py
phlower/nn/_core_modules/_en_equivariant_tcn.py
phlower/nn/_core_modules/_gcn.py
phlower/nn/_core_modules/_identity.py
phlower/nn/_core_modules/_iso_gcn.py
phlower-0.3.0.dist-info/METADATA
phlower-0.3.0.dist-info/WHEEL
phlower-0.3.0.dist-info/licenses/LICENSE
phlower-0.3.0.dist-info/RECORD
