Metadata-Version: 2.4
Name: phlower
Version: 0.3.0
Summary: This is a Python package which helps you handle GNN especially for physics problems.
License-Expression: Apache-2.0
License-File: LICENSE
Author: RICOS Co. Ltd.
Maintainer: Riku Sakamoto
Maintainer-email: sakamoto@ricos.co.jp
Requires-Python: >=3.10,<4.0
Classifier: Programming Language :: Python :: 3
Classifier: Programming Language :: Python :: 3.10
Classifier: Programming Language :: Python :: 3.11
Classifier: Programming Language :: Python :: 3.12
Classifier: Programming Language :: Python :: 3.13
Classifier: Programming Language :: Python :: 3.14
Requires-Dist: dagstream (>=0.1.5)
Requires-Dist: einops (>=0.8.0)
Requires-Dist: pandas (>=2.2.2)
Requires-Dist: pipe (>=2.2,<3.0)
Requires-Dist: pycryptodomex (>=3.20.0,<4.0.0)
Requires-Dist: pydantic (>=2.7.0,<3)
Requires-Dist: pyvista (>=0.43.10,<1)
Requires-Dist: pyyaml (>=6.0.1)
Requires-Dist: scikit-learn (>=1.5.0,<2)
Requires-Dist: scipy (>=1.13.0,<2)
Requires-Dist: torch (>=2.5.0,<3.0.0)
Requires-Dist: torchvision (>=0.20.1)
Requires-Dist: tqdm (>=4.66.4)
